odoo/addons/account_payment_batch_process_discount/README.rst
odoo/addons/account_payment_batch_process_discount/__init__.py
odoo/addons/account_payment_batch_process_discount/__manifest__.py
odoo/addons/account_payment_batch_process_discount/i18n/account_payment_batch_process_discount.pot
odoo/addons/account_payment_batch_process_discount/models/__init__.py
odoo/addons/account_payment_batch_process_discount/models/account_move.py
odoo/addons/account_payment_batch_process_discount/models/account_payment_term_line.py
odoo/addons/account_payment_batch_process_discount/readme/CONFIGURE.rst
odoo/addons/account_payment_batch_process_discount/readme/CONTRIBUTORS.rst
odoo/addons/account_payment_batch_process_discount/readme/DESCRIPTION.rst
odoo/addons/account_payment_batch_process_discount/readme/USAGE.rst
odoo/addons/account_payment_batch_process_discount/static/description/icon.png
odoo/addons/account_payment_batch_process_discount/static/description/index.html
odoo/addons/account_payment_batch_process_discount/views/account_move.xml
odoo/addons/account_payment_batch_process_discount/wizard/__init__.py
odoo/addons/account_payment_batch_process_discount/wizard/account_payment_register.py
odoo/addons/account_payment_batch_process_discount/wizard/invoice_payment_line.py
odoo14_addon_account_payment_batch_process_discount-14.0.1.0.1.dist-info/METADATA
odoo14_addon_account_payment_batch_process_discount-14.0.1.0.1.dist-info/WHEEL
odoo14_addon_account_payment_batch_process_discount-14.0.1.0.1.dist-info/top_level.txt
odoo14_addon_account_payment_batch_process_discount-14.0.1.0.1.dist-info/RECORD
